dynamicts/__init__.py
dynamicts/analysis.py
dynamicts/analysis_helpers.py
dynamicts/data_loader.py
dynamicts/dynamic_analysis.py
dynamicts/lag_correlation.py
dynamicts/report_generator.py
dynamicts/report_generator_sh.py
dynamicts/stationarity.py
dynamicts/volatility_check.py
dynamicts-0.2.3.dist-info/METADATA
dynamicts-0.2.3.dist-info/WHEEL
dynamicts-0.2.3.dist-info/top_level.txt
dynamicts-0.2.3.dist-info/RECORD
